<?xml version="1.0" encoding="utf-8" ?><dwsync><file name="effects.js" server="atlanta1996.us" local="3843317033" remote="3496363200" Dst="-1" /><file name="js_gfunctions.js" server="atlanta1996.us" local="3843317033" remote="3496363200" Dst="-1" /><file name="lightbox.js" server="atlanta1996.us" local="3843317033" remote="3496363200" Dst="-1" /><file name="nicEdit.js" server="atlanta1996.us" local="3843317033" remote="3496363200" Dst="-1" /><file name="scriptaculous.js" server="atlanta1996.us" local="3843317037" remote="3496363200" Dst="-1" /><file name="prototype.js" server="atlanta1996.us" local="3843317037" remote="3496363200" Dst="-1" /><file name="swfobject.js" server="atlanta1996.us" local="3843317038" remote="3496363200" Dst="-1" /><file name="tinyMCEbasicText.js" server="atlanta1996.us" local="3843317038" remote="3496363200" Dst="-1" /><file name="tinyMCEbasicText.php" server="atlanta1996.us" local="3843317039" remote="3496363200" Dst="-1" /><file name="tinyMCErichText.js" server="atlanta1996.us" local="3843317039" remote="3496363200" Dst="-1" /><file name="tinyMCErichText.php" server="atlanta1996.us" local="3843317041" remote="3496363200" Dst="-1" /></dwsync>